decoupage_libelles/__init__.py
decoupage_libelles/main.py
decoupage_libelles/config/__init__.py
decoupage_libelles/config/logger_configuration.py
decoupage_libelles/config/settings_configuration.py
decoupage_libelles/config/type_voie_decoupage_launcher.py
decoupage_libelles/data/__init__.py
decoupage_libelles/data/code2lib.json
decoupage_libelles/data/type_voie.csv
decoupage_libelles/decoupe_voie/__init__.py
decoupage_libelles/decoupe_voie/model/__init__.py
decoupage_libelles/decoupe_voie/model/voie_decoupee.py
decoupage_libelles/decoupe_voie/usecase/__init__.py
decoupage_libelles/decoupe_voie/usecase/assign_compl_type_lib_compl_use_case.py
decoupage_libelles/decoupe_voie/usecase/assign_compl_type_lib_use_case.py
decoupage_libelles/decoupe_voie/usecase/assign_lib_compl_use_case.py
decoupage_libelles/decoupe_voie/usecase/assign_lib_type_use_case.py
decoupage_libelles/decoupe_voie/usecase/assign_lib_use_case.py
decoupage_libelles/decoupe_voie/usecase/assign_type_lib_compl_use_case.py
decoupage_libelles/decoupe_voie/usecase/assign_type_lib_use_case.py
decoupage_libelles/decoupe_voie/usecase/assign_type_use_case.py
decoupage_libelles/decoupe_voie/usecase/dilated_voie_decoupee_use_case.py
decoupage_libelles/entrypoints/__init__.py
decoupage_libelles/entrypoints/web/__init__.py
decoupage_libelles/entrypoints/web/main_api.py
decoupage_libelles/finders/find_complement/__init__.py
decoupage_libelles/finders/find_complement/usecase/__init__.py
decoupage_libelles/finders/find_complement/usecase/apply_complement_finder_on_voies_use_case.py
decoupage_libelles/finders/find_complement/usecase/complement_finder_use_case.py
decoupage_libelles/finders/find_type/__init__.py
decoupage_libelles/finders/find_type/model/__init__.py
decoupage_libelles/finders/find_type/model/type_finder_object.py
decoupage_libelles/finders/find_type/model/type_finder_utils.py
decoupage_libelles/finders/find_type/usecase/__init__.py
decoupage_libelles-0.1.1.dist-info/licenses/LICENSE
decoupage_libelles-0.1.1.dist-info/METADATA
decoupage_libelles-0.1.1.dist-info/WHEEL
decoupage_libelles-0.1.1.dist-info/top_level.txt
decoupage_libelles-0.1.1.dist-info/RECORD
