Metadata-Version: 2.4
Name: decoupage_libelles
Version: 0.1.1
Summary: Algorithme NLP de découpage d'un nom de voie en type de voie + nom de voie + complément adresse
Author-email: Raya Berova <raya.berova@insee.fr>
License: MIT
Project-URL: Homepage, https://github.com/InseeFrLab/gaia-decoupage-nom-voie/
Project-URL: Issues, https://github.com/InseeFrLab/gaia-decoupage-nom-voie/issues
Requires-Python: >=3.13
License-File: LICENSE
Requires-Dist: fastapi==0.110.0
Requires-Dist: httpx==0.27.0
Requires-Dist: pandas==2.3.1
Requires-Dist: unidecode==1.3.8
Requires-Dist: dynaconf==3.2.1
Requires-Dist: tqdm==4.66.1
Requires-Dist: spacy==3.8.7
Requires-Dist: transformers==4.54.1
Requires-Dist: spacy-curated-transformers==0.2.2
Requires-Dist: uvicorn==0.34.0
Requires-Dist: fsspec==2025.10.0
Requires-Dist: torch==2.6.0
Dynamic: license-file
